MANIFEST.in
README.rst
VERSION
setup.cfg
setup.py
pynaut/__init__.py
pynaut/main.py
pynaut.egg-info/PKG-INFO
pynaut.egg-info/SOURCES.txt
pynaut.egg-info/dependency_links.txt
pynaut.egg-info/entry_points.txt
pynaut.egg-info/top_level.txt
pynaut/ui/__init__.py
pynaut/ui/main.py
test/data.py
test/test_all.py