Metadata-Version: 1.1
Name: pynaut
Version: 0.2.13
Summary: A tool for recursively exploring arbitrary python objects.
Home-page: https://github.com/stnbu/pynaut
Author: Mike Burr
Author-email: mburr@unintuitive.org
License: MIT
Download-URL: https://github.com/stnbu/pynaut/archive/master.zip
Keywords: introspection,debugging
Platform: UNKNOWN
Classifier: Development Status :: 4 - Beta
Classifier: Intended Audience :: Developers
Classifier: License :: OSI Approved :: MIT License
Classifier: Programming Language :: Python :: 2
Classifier: Topic :: Software Development :: Debuggers
Classifier: Topic :: Software Development :: Testing
Classifier: Topic :: Software Development
Classifier: Topic :: Utilities
Requires: urwid
Requires: UniCurses
Provides: pynaut
